nonebot_plugin_extrautils/__init__.py
nonebot_plugin_extrautils/misc.py
nonebot_plugin_extrautils/ob11/__init__.py
nonebot_plugin_extrautils/ob11/gocq.py
nonebot_plugin_extrautils/ob11/universal.py
nonebot_plugin_extrautils-0.2.1.dist-info/LICENSE
nonebot_plugin_extrautils-0.2.1.dist-info/METADATA
nonebot_plugin_extrautils-0.2.1.dist-info/WHEEL
nonebot_plugin_extrautils-0.2.1.dist-info/top_level.txt
nonebot_plugin_extrautils-0.2.1.dist-info/RECORD
