Metadata-Version: 2.1
Name: nonebot-plugin-extrautils
Version: 0.2.1
Summary: Extra utility functions for easier development with nonebot2
Author-email: HivertMoZara <worldmozara@163.com>
License: MIT
Project-URL: Homepage, https://github.com/NCBM/nonebot-plugin-extrautils
Project-URL: Repository, https://github.com/NCBM/nonebot-plugin-extrautils
Requires-Python: >=3.8
License-File: LICENSE
Requires-Dist: nonebot2 (>=2.0.0b1)
Requires-Dist: nonebot-adapter-onebot (>=2.1)
Requires-Dist: httpx (>=0.23)
